agentbox/__init__.py
agentboxsdk-0.0.1.dist-info/METADATA
agentboxsdk-0.0.1.dist-info/WHEEL
agentboxsdk-0.0.1.dist-info/top_level.txt
agentboxsdk-0.0.1.dist-info/RECORD
