Metadata-Version: 2.4
Name: agentboxsdk
Version: 0.0.1
Summary: A modular AI Agent
Author-email: Shantanu Dutta <shantanudb.cloud@gmail.com>
License: Proprietary
Requires-Python: >=3.12
